neuroshape/__init__.py
neuroshape/_stats.cpython-310-darwin.so
neuroshape/connectopic_laplacian.py
neuroshape/eigenmaps.py
neuroshape/eta.cpython-310-darwin.so
neuroshape/euler.cpython-310-darwin.so
neuroshape/permutation.py
neuroshape/poly_eigenmaps.py
neuroshape/stats.cpython-310-darwin.so
neuroshape/stats.py
neuroshape/volume_eigenmodes.py
neuroshape/nulls/__init__.py
neuroshape/nulls/burt.py
neuroshape/nulls/eigenshuff.py
neuroshape/nulls/nulls.py
neuroshape/nulls/spins.py
neuroshape/nulls/waveshuff.py
neuroshape/utils/__init__.py
neuroshape/utils/check_fs_subjid.py
neuroshape/utils/check_map.py
neuroshape/utils/checks.py
neuroshape/utils/compare_parallel.py
neuroshape/utils/compute_geodesic_distance.py
neuroshape/utils/concavehull.py
neuroshape/utils/eigen.py
neuroshape/utils/fs_shapeDNA.py
neuroshape/utils/geometry.py
neuroshape/utils/load_mesh_vertices.py
neuroshape/utils/meshtransforms.py
neuroshape/utils/swap_single_row.py
neuroshape/utils/tmpname.py
neuroshape/utils/zscore_avg_method.py
neuroshape-0.0.3.dist-info/LICENSE
neuroshape-0.0.3.dist-info/METADATA
neuroshape-0.0.3.dist-info/WHEEL
neuroshape-0.0.3.dist-info/top_level.txt
neuroshape-0.0.3.dist-info/RECORD
